zlib_fast/__init__.py
zlib_fast/const.py
zlib_fast/gzip_adapter.py
zlib_fast/py.typed
zlib_fast/utils.py
zlib_fast/zlib_adapter.py
zlib_fast-0.2.1.dist-info/LICENSE
zlib_fast-0.2.1.dist-info/METADATA
zlib_fast-0.2.1.dist-info/WHEEL
zlib_fast-0.2.1.dist-info/RECORD
