Metadata-Version: 2.3
Name: zlib-fast
Version: 0.2.1
Summary: A wrapper to use the fastest available zlib
License: Apache Software License 2.0
Author: J. Nick Koston
Author-email: nick@koston.org
Requires-Python: >=3.9,<4.0
Classifier: Development Status :: 2 - Pre-Alpha
Classifier: Intended Audience :: Developers
Classifier: License :: Other/Proprietary License
Classifier: Natural Language :: English
Classifier: Operating System :: OS Independent
Classifier: Programming Language :: Python :: 3
Classifier: Programming Language :: Python :: 3.9
Classifier: Programming Language :: Python :: 3.10
Classifier: Programming Language :: Python :: 3.11
Classifier: Programming Language :: Python :: 3.12
Classifier: Programming Language :: Python :: 3.13
Classifier: Topic :: Software Development :: Libraries
Requires-Dist: isal (>=1.5.3)
Project-URL: Bug Tracker, https://github.com/bluetooth-devices/zlib-fast/issues
Project-URL: Changelog, https://github.com/bluetooth-devices/zlib-fast/blob/main/CHANGELOG.md
Project-URL: Documentation, https://zlib-fast.readthedocs.io
Project-URL: Repository, https://github.com/bluetooth-devices/zlib-fast
